{"id": "7515521402238192918", "formats": [{"ext": "mp4", "vcodec": "h264", "acodec": "aac", "format_id": "download", "url": "https://v16-webapp-prime.us.tiktok.com/video/tos/no1a/tos-no1a-ve-0068-no/o4oEfJFTuID2ynQAzsGgfZEaoMEaR4pFkBbH1B/?a=1988&bti=ODszNWYuMDE6&ch=0&cr=3&dr=0&lr=all&cd=0%7C0%7C0%7C&cv=1&br=1094&bt=547&cs=0&ds=3&ft=4KJMyMzm8Zmo08eRcI4jV1GjdpWrKsd.&mime_type=video_mp4&qs=0&rc=ZTRoODU3aTg6NTpkZDxpZkBpM2htbW05cnY6NDMzbzczNUAuYDQ2LWNgXl4xXzU2NV4wYSNqczNqMmRrbTNhLS1kMTFzcw%3D%3D&btag=e000b8000&expire=1754625598&l=20250806035941B7B3D5CB1653D912298F&ply_type=2&policy=2&signature=88b58a329f1a0d9d492eab92426bbce3&tk=tt_chain_token", "format_note": "watermarked", "preference": -2, "protocol": "https", "video_ext": "mp4", "audio_ext": "none", "dynamic_range": "SDR", "cookies": "ttwid=1%7ChRi4t0oz-ovVHan5D4N9WD8bWR7Ly3h4oIN--zpKnjM%7C1754452781%7C55b62b40bbf621655ff23ccdd1c622e224871e5c0b32ba6c197c99162a5af0be; Domain=.tiktok.com; Path=/; Expires=1785556781; tt_csrf_token=auPX6IOX-v4ir3CbOFg6Te5XH0ZAu-FjGB7k; Domain=.tiktok.com; Path=/; Secure; tt_chain_token=\"qV5Gmh09CAgPzrFqFuxExA==\"; Domain=.tiktok.com; Path=/; Secure; Expires=1770004781", "http_headers": {"User-Agent": "Mozilla/5.0 (iPhone; CPU iPhone OS 14_6 like Mac OS X) AppleWebKit/605.1.15 (KHTML, like Gecko) Version/14.1.1 Mobile/15E148 Safari/604.1", "Accept": "*/*", "Accept-Language": "en-US,en;q=0.9", "Sec-Fetch-Mode": "navigate", "Accept-Encoding": "gzip, deflate", "Connection": "keep-alive", "Referer": "https://www.tiktok.com/@colorflowlab/video/7515521402238192918"}, "format": "download - unknown (watermarked)"}, {"ext": "mp4", "vcodec": "h264", "acodec": "aac", "format_id": "h264_540p_306200-0", "tbr": 306, "quality": 1, "preference": -1, "filesize": 627712, "width": 576, "height": 1024, "url": "https://v16-webapp-prime.us.tiktok.com/video/tos/no1a/tos-no1a-ve-0068c001-no/oEnjl1Am8AAbxnJSMMjQmeDheQLIWIA9pPohed/?a=1988&bti=ODszNWYuMDE6&ch=0&cr=3&dr=0&lr=all&cd=0%7C0%7C0%7C&cv=1&br=598&bt=299&cs=0&ds=6&ft=4KJMyMzm8Zmo08eRcI4jV1GjdpWrKsd.&mime_type=video_mp4&qs=4&rc=ZzQ0ZzVkOjc7Ozs7NDQ2OkBpM2htbW05cnY6NDMzbzczNUBjLWAxMWM2Ni4xNWNfMzExYSNqczNqMmRrbTNhLS1kMTFzcw%3D%3D&btag=e000b8000&expire=1754625598&l=20250806035941B7B3D5CB1653D912298F&ply_type=2&policy=2&signature=d7bda6614c630e0db568ba4979383737&tk=tt_chain_token", "protocol": "https", "video_ext": "mp4", "audio_ext": "none", "resolution": "576x1024", "dynamic_range": "SDR", "aspect_ratio": 0.56, "cookies": "ttwid=1%7ChRi4t0oz-ovVHan5D4N9WD8bWR7Ly3h4oIN--zpKnjM%7C1754452781%7C55b62b40bbf621655ff23ccdd1c622e224871e5c0b32ba6c197c99162a5af0be; Domain=.tiktok.com; Path=/; Expires=1785556781; tt_csrf_token=auPX6IOX-v4ir3CbOFg6Te5XH0ZAu-FjGB7k; Domain=.tiktok.com; Path=/; Secure; tt_chain_token=\"qV5Gmh09CAgPzrFqFuxExA==\"; Domain=.tiktok.com; Path=/; Secure; Expires=1770004781", "http_headers": {"User-Agent": "Mozilla/5.0 (iPhone; CPU iPhone OS 14_6 like Mac OS X) AppleWebKit/605.1.15 (KHTML, like Gecko) Version/14.1.1 Mobile/15E148 Safari/604.1", "Accept": "*/*", "Accept-Language": "en-US,en;q=0.9", "Sec-Fetch-Mode": "navigate", "Accept-Encoding": "gzip, deflate", "Connection": "keep-alive", "Referer": "https://www.tiktok.com/@colorflowlab/video/7515521402238192918"}, "format": "h264_540p_306200-0 - 576x1024"}, {"ext": "mp4", "vcodec": "h264", "acodec": "aac", "format_id": "h264_540p_306200-1", "tbr": 306, "quality": 1, "preference": -1, "filesize": 627712, "width": 576, "height": 1024, "url": "https://v19-webapp-prime.us.tiktok.com/video/tos/no1a/tos-no1a-ve-0068c001-no/oEnjl1Am8AAbxnJSMMjQmeDheQLIWIA9pPohed/?a=1988&bti=ODszNWYuMDE6&ch=0&cr=3&dr=0&lr=all&cd=0%7C0%7C0%7C&cv=1&br=598&bt=299&cs=0&ds=6&ft=4KJMyMzm8Zmo08eRcI4jV1GjdpWrKsd.&mime_type=video_mp4&qs=4&rc=ZzQ0ZzVkOjc7Ozs7NDQ2OkBpM2htbW05cnY6NDMzbzczNUBjLWAxMWM2Ni4xNWNfMzExYSNqczNqMmRrbTNhLS1kMTFzcw%3D%3D&btag=e000b8000&expire=1754625598&l=20250806035941B7B3D5CB1653D912298F&ply_type=2&policy=2&signature=d7bda6614c630e0db568ba4979383737&tk=tt_chain_token", "protocol": "https", "video_ext": "mp4", "audio_ext": "none", "resolution": "576x1024", "dynamic_range": "SDR", "aspect_ratio": 0.56, "cookies": "ttwid=1%7ChRi4t0oz-ovVHan5D4N9WD8bWR7Ly3h4oIN--zpKnjM%7C1754452781%7C55b62b40bbf621655ff23ccdd1c622e224871e5c0b32ba6c197c99162a5af0be; Domain=.tiktok.com; Path=/; Expires=1785556781; tt_csrf_token=auPX6IOX-v4ir3CbOFg6Te5XH0ZAu-FjGB7k; Domain=.tiktok.com; Path=/; Secure; tt_chain_token=\"qV5Gmh09CAgPzrFqFuxExA==\"; Domain=.tiktok.com; Path=/; Secure; Expires=1770004781", "http_headers": {"User-Agent": "Mozilla/5.0 (iPhone; CPU iPhone OS 14_6 like Mac OS X) AppleWebKit/605.1.15 (KHTML, like Gecko) Version/14.1.1 Mobile/15E148 Safari/604.1", "Accept": "*/*", "Accept-Language": "en-US,en;q=0.9", "Sec-Fetch-Mode": "navigate", "Accept-Encoding": "gzip, deflate", "Connection": "keep-alive", "Referer": "https://www.tiktok.com/@colorflowlab/video/7515521402238192918"}, "format": "h264_540p_306200-1 - 576x1024"}, {"ext": "mp4", "vcodec": "h264", "acodec": "aac", "format_id": "h264_540p_535598-0", "tbr": 535, "quality": 1, "preference": -1, "filesize": 1097977, "width": 576, "height": 1024, "url": "https://v16-webapp-prime.us.tiktok.com/video/tos/no1a/tos-no1a-ve-0068c001-no/ooCGdPIIQLAQlAmezfLIYpCfYvnTRIA0GDPjgO/?a=1988&bti=ODszNWYuMDE6&ch=0&cr=3&dr=0&lr=all&cd=0%7C0%7C0%7C&cv=1&br=1046&bt=523&cs=0&ds=6&ft=4KJMyMzm8Zmo08eRcI4jV1GjdpWrKsd.&mime_type=video_mp4&qs=0&rc=PDxlNzVlNzxmN2U6ZmVnPEBpM2htbW05cnY6NDMzbzczNUBiYzI1MS8tXjMxLS8tYS4yYSNqczNqMmRrbTNhLS1kMTFzcw%3D%3D&btag=e000b8000&expire=1754625598&l=20250806035941B7B3D5CB1653D912298F&ply_type=2&policy=2&signature=56960c2dca1ad46c43e1011eb22f73dc&tk=tt_chain_token", "protocol": "https", "video_ext": "mp4", "audio_ext": "none", "resolution": "576x1024", "dynamic_range": "SDR", "aspect_ratio": 0.56, "cookies": "ttwid=1%7ChRi4t0oz-ovVHan5D4N9WD8bWR7Ly3h4oIN--zpKnjM%7C1754452781%7C55b62b40bbf621655ff23ccdd1c622e224871e5c0b32ba6c197c99162a5af0be; Domain=.tiktok.com; Path=/; Expires=1785556781; tt_csrf_token=auPX6IOX-v4ir3CbOFg6Te5XH0ZAu-FjGB7k; Domain=.tiktok.com; Path=/; Secure; tt_chain_token=\"qV5Gmh09CAgPzrFqFuxExA==\"; Domain=.tiktok.com; Path=/; Secure; Expires=1770004781", "http_headers": {"User-Agent": "Mozilla/5.0 (iPhone; CPU iPhone OS 14_6 like Mac OS X) AppleWebKit/605.1.15 (KHTML, like Gecko) Version/14.1.1 Mobile/15E148 Safari/604.1", "Accept": "*/*", "Accept-Language": "en-US,en;q=0.9", "Sec-Fetch-Mode": "navigate", "Accept-Encoding": "gzip, deflate", "Connection": "keep-alive", "Referer": "https://www.tiktok.com/@colorflowlab/video/7515521402238192918"}, "format": "h264_540p_535598-0 - 576x1024"}, {"ext": "mp4", "vcodec": "h264", "acodec": "aac", "format_id": "h264_540p_535598-1", "tbr": 535, "quality": 1, "preference": -1, "filesize": 1097977, "width": 576, "height": 1024, "url": "https://v19-webapp-prime.us.tiktok.com/video/tos/no1a/tos-no1a-ve-0068c001-no/ooCGdPIIQLAQlAmezfLIYpCfYvnTRIA0GDPjgO/?a=1988&bti=ODszNWYuMDE6&ch=0&cr=3&dr=0&lr=all&cd=0%7C0%7C0%7C&cv=1&br=1046&bt=523&cs=0&ds=6&ft=4KJMyMzm8Zmo08eRcI4jV1GjdpWrKsd.&mime_type=video_mp4&qs=0&rc=PDxlNzVlNzxmN2U6ZmVnPEBpM2htbW05cnY6NDMzbzczNUBiYzI1MS8tXjMxLS8tYS4yYSNqczNqMmRrbTNhLS1kMTFzcw%3D%3D&btag=e000b8000&expire=1754625598&l=20250806035941B7B3D5CB1653D912298F&ply_type=2&policy=2&signature=56960c2dca1ad46c43e1011eb22f73dc&tk=tt_chain_token", "protocol": "https", "video_ext": "mp4", "audio_ext": "none", "resolution": "576x1024", "dynamic_range": "SDR", "aspect_ratio": 0.56, "cookies": "ttwid=1%7ChRi4t0oz-ovVHan5D4N9WD8bWR7Ly3h4oIN--zpKnjM%7C1754452781%7C55b62b40bbf621655ff23ccdd1c622e224871e5c0b32ba6c197c99162a5af0be; Domain=.tiktok.com; Path=/; Expires=1785556781; tt_csrf_token=auPX6IOX-v4ir3CbOFg6Te5XH0ZAu-FjGB7k; Domain=.tiktok.com; Path=/; Secure; tt_chain_token=\"qV5Gmh09CAgPzrFqFuxExA==\"; Domain=.tiktok.com; Path=/; Secure; Expires=1770004781", "http_headers": {"User-Agent": "Mozilla/5.0 (iPhone; CPU iPhone OS 14_6 like Mac OS X) AppleWebKit/605.1.15 (KHTML, like Gecko) Version/14.1.1 Mobile/15E148 Safari/604.1", "Accept": "*/*", "Accept-Language": "en-US,en;q=0.9", "Sec-Fetch-Mode": "navigate", "Accept-Encoding": "gzip, deflate", "Connection": "keep-alive", "Referer": "https://www.tiktok.com/@colorflowlab/video/7515521402238192918"}, "format": "h264_540p_535598-1 - 576x1024"}, {"ext": "mp4", "vcodec": "h265", "acodec": "aac", "format_id": "bytevc1_540p_340947-0", "tbr": 340, "quality": 1, "preference": -1, "filesize": 698942, "width": 576, "height": 1024, "url": "https://v16-webapp-prime.us.tiktok.com/video/tos/no1a/tos-no1a-ve-0068c001-no/os8QfejkIQMmnxLQgfWnlgP1LwqmQADdP6qIpA/?a=1988&bti=ODszNWYuMDE6&ch=0&cr=3&dr=0&lr=all&cd=0%7C0%7C0%7C&cv=1&br=664&bt=332&cs=2&ds=6&ft=4KJMyMzm8Zmo08eRcI4jV1GjdpWrKsd.&mime_type=video_mp4&qs=11&rc=NWk7OTVkM2lpZzQ8OTlkN0BpM2htbW05cnY6NDMzbzczNUBhY2JgMWExNl4xYGIwMV80YSNqczNqMmRrbTNhLS1kMTFzcw%3D%3D&btag=e000b8000&expire=1754625598&l=20250806035941B7B3D5CB1653D912298F&ply_type=2&policy=2&signature=4047c864808ed344bd4c6cd638d60375&tk=tt_chain_token", "protocol": "https", "video_ext": "mp4", "audio_ext": "none", "resolution": "576x1024", "dynamic_range": "SDR", "aspect_ratio": 0.56, "cookies": "ttwid=1%7ChRi4t0oz-ovVHan5D4N9WD8bWR7Ly3h4oIN--zpKnjM%7C1754452781%7C55b62b40bbf621655ff23ccdd1c622e224871e5c0b32ba6c197c99162a5af0be; Domain=.tiktok.com; Path=/; Expires=1785556781; tt_csrf_token=auPX6IOX-v4ir3CbOFg6Te5XH0ZAu-FjGB7k; Domain=.tiktok.com; Path=/; Secure; tt_chain_token=\"qV5Gmh09CAgPzrFqFuxExA==\"; Domain=.tiktok.com; Path=/; Secure; Expires=1770004781", "http_headers": {"User-Agent": "Mozilla/5.0 (iPhone; CPU iPhone OS 14_6 like Mac OS X) AppleWebKit/605.1.15 (KHTML, like Gecko) Version/14.1.1 Mobile/15E148 Safari/604.1", "Accept": "*/*", "Accept-Language": "en-US,en;q=0.9", "Sec-Fetch-Mode": "navigate", "Accept-Encoding": "gzip, deflate", "Connection": "keep-alive", "Referer": "https://www.tiktok.com/@colorflowlab/video/7515521402238192918"}, "format": "bytevc1_540p_340947-0 - 576x1024"}, {"ext": "mp4", "vcodec": "h265", "acodec": "aac", "format_id": "bytevc1_540p_340947-1", "tbr": 340, "quality": 1, "preference": -1, "filesize": 698942, "width": 576, "height": 1024, "url": "https://v19-webapp-prime.us.tiktok.com/video/tos/no1a/tos-no1a-ve-0068c001-no/os8QfejkIQMmnxLQgfWnlgP1LwqmQADdP6qIpA/?a=1988&bti=ODszNWYuMDE6&ch=0&cr=3&dr=0&lr=all&cd=0%7C0%7C0%7C&cv=1&br=664&bt=332&cs=2&ds=6&ft=4KJMyMzm8Zmo08eRcI4jV1GjdpWrKsd.&mime_type=video_mp4&qs=11&rc=NWk7OTVkM2lpZzQ8OTlkN0BpM2htbW05cnY6NDMzbzczNUBhY2JgMWExNl4xYGIwMV80YSNqczNqMmRrbTNhLS1kMTFzcw%3D%3D&btag=e000b8000&expire=1754625598&l=20250806035941B7B3D5CB1653D912298F&ply_type=2&policy=2&signature=4047c864808ed344bd4c6cd638d60375&tk=tt_chain_token", "protocol": "https", "video_ext": "mp4", "audio_ext": "none", "resolution": "576x1024", "dynamic_range": "SDR", "aspect_ratio": 0.56, "cookies": "ttwid=1%7ChRi4t0oz-ovVHan5D4N9WD8bWR7Ly3h4oIN--zpKnjM%7C1754452781%7C55b62b40bbf621655ff23ccdd1c622e224871e5c0b32ba6c197c99162a5af0be; Domain=.tiktok.com; Path=/; Expires=1785556781; tt_csrf_token=auPX6IOX-v4ir3CbOFg6Te5XH0ZAu-FjGB7k; Domain=.tiktok.com; Path=/; Secure; tt_chain_token=\"qV5Gmh09CAgPzrFqFuxExA==\"; Domain=.tiktok.com; Path=/; Secure; Expires=1770004781", "http_headers": {"User-Agent": "Mozilla/5.0 (iPhone; CPU iPhone OS 14_6 like Mac OS X) AppleWebKit/605.1.15 (KHTML, like Gecko) Version/14.1.1 Mobile/15E148 Safari/604.1", "Accept": "*/*", "Accept-Language": "en-US,en;q=0.9", "Sec-Fetch-Mode": "navigate", "Accept-Encoding": "gzip, deflate", "Connection": "keep-alive", "Referer": "https://www.tiktok.com/@colorflowlab/video/7515521402238192918"}, "format": "bytevc1_540p_340947-1 - 576x1024"}, {"ext": "mp4", "vcodec": "h265", "acodec": "aac", "format_id": "bytevc1_720p_426758-0", "tbr": 426, "quality": 2, "preference": -1, "filesize": 874854, "width": 720, "height": 1280, "url": "https://v16-webapp-prime.us.tiktok.com/video/tos/no1a/tos-no1a-ve-0068-no/oEZ1PQZlxdQAwFffm8QkDWmIjL4MpAnIng8ke6/?a=1988&bti=ODszNWYuMDE6&ch=0&cr=3&dr=0&lr=all&cd=0%7C0%7C0%7C&cv=1&br=832&bt=416&cs=2&ds=3&ft=4KJMyMzm8Zmo08eRcI4jV1GjdpWrKsd.&mime_type=video_mp4&qs=14&rc=ZDc5ZGg1OTk7ZDZkODY5OkBpM2htbW05cnY6NDMzbzczNUAtLWIzLTUxNjMxLzYxLWMzYSNqczNqMmRrbTNhLS1kMTFzcw%3D%3D&btag=e000b8000&expire=1754625598&l=20250806035941B7B3D5CB1653D912298F&ply_type=2&policy=2&signature=75f23ad62fe2ce69cf0a5d35b2bf51c9&tk=tt_chain_token", "protocol": "https", "video_ext": "mp4", "audio_ext": "none", "resolution": "720x1280", "dynamic_range": "SDR", "aspect_ratio": 0.56, "cookies": "ttwid=1%7ChRi4t0oz-ovVHan5D4N9WD8bWR7Ly3h4oIN--zpKnjM%7C1754452781%7C55b62b40bbf621655ff23ccdd1c622e224871e5c0b32ba6c197c99162a5af0be; Domain=.tiktok.com; Path=/; Expires=1785556781; tt_csrf_token=auPX6IOX-v4ir3CbOFg6Te5XH0ZAu-FjGB7k; Domain=.tiktok.com; Path=/; Secure; tt_chain_token=\"qV5Gmh09CAgPzrFqFuxExA==\"; Domain=.tiktok.com; Path=/; Secure; Expires=1770004781", "http_headers": {"User-Agent": "Mozilla/5.0 (iPhone; CPU iPhone OS 14_6 like Mac OS X) AppleWebKit/605.1.15 (KHTML, like Gecko) Version/14.1.1 Mobile/15E148 Safari/604.1", "Accept": "*/*", "Accept-Language": "en-US,en;q=0.9", "Sec-Fetch-Mode": "navigate", "Accept-Encoding": "gzip, deflate", "Connection": "keep-alive", "Referer": "https://www.tiktok.com/@colorflowlab/video/7515521402238192918"}, "format": "bytevc1_720p_426758-0 - 720x1280"}, {"ext": "mp4", "vcodec": "h265", "acodec": "aac", "format_id": "bytevc1_720p_426758-1", "tbr": 426, "quality": 2, "preference": -1, "filesize": 874854, "width": 720, "height": 1280, "url": "https://v19-webapp-prime.us.tiktok.com/video/tos/no1a/tos-no1a-ve-0068-no/oEZ1PQZlxdQAwFffm8QkDWmIjL4MpAnIng8ke6/?a=1988&bti=ODszNWYuMDE6&ch=0&cr=3&dr=0&lr=all&cd=0%7C0%7C0%7C&cv=1&br=832&bt=416&cs=2&ds=3&ft=4KJMyMzm8Zmo08eRcI4jV1GjdpWrKsd.&mime_type=video_mp4&qs=14&rc=ZDc5ZGg1OTk7ZDZkODY5OkBpM2htbW05cnY6NDMzbzczNUAtLWIzLTUxNjMxLzYxLWMzYSNqczNqMmRrbTNhLS1kMTFzcw%3D%3D&btag=e000b8000&expire=1754625598&l=20250806035941B7B3D5CB1653D912298F&ply_type=2&policy=2&signature=75f23ad62fe2ce69cf0a5d35b2bf51c9&tk=tt_chain_token", "protocol": "https", "video_ext": "mp4", "audio_ext": "none", "resolution": "720x1280", "dynamic_range": "SDR", "aspect_ratio": 0.56, "cookies": "ttwid=1%7ChRi4t0oz-ovVHan5D4N9WD8bWR7Ly3h4oIN--zpKnjM%7C1754452781%7C55b62b40bbf621655ff23ccdd1c622e224871e5c0b32ba6c197c99162a5af0be; Domain=.tiktok.com; Path=/; Expires=1785556781; tt_csrf_token=auPX6IOX-v4ir3CbOFg6Te5XH0ZAu-FjGB7k; Domain=.tiktok.com; Path=/; Secure; tt_chain_token=\"qV5Gmh09CAgPzrFqFuxExA==\"; Domain=.tiktok.com; Path=/; Secure; Expires=1770004781", "http_headers": {"User-Agent": "Mozilla/5.0 (iPhone; CPU iPhone OS 14_6 like Mac OS X) AppleWebKit/605.1.15 (KHTML, like Gecko) Version/14.1.1 Mobile/15E148 Safari/604.1", "Accept": "*/*", "Accept-Language": "en-US,en;q=0.9", "Sec-Fetch-Mode": "navigate", "Accept-Encoding": "gzip, deflate", "Connection": "keep-alive", "Referer": "https://www.tiktok.com/@colorflowlab/video/7515521402238192918"}, "format": "bytevc1_720p_426758-1 - 720x1280"}, {"ext": "mp4", "vcodec": "h265", "acodec": "aac", "format_id": "bytevc1_1080p_753210-0", "tbr": 753, "quality": 3, "preference": -1, "filesize": 1541352, "width": 1080, "height": 1920, "url": "https://v16-webapp-prime.us.tiktok.com/video/tos/no1a/tos-no1a-ve-0068-no/ooQenFjIgLA8eRU0AQ4AmwpeIDWn6JmMPiYlcd/?a=1988&bti=ODszNWYuMDE6&ch=0&cr=3&dr=0&lr=all&cd=0%7C0%7C0%7C&cv=1&br=1470&bt=735&cs=2&ds=4&ft=4KJMyMzm8Zmo08eRcI4jV1GjdpWrKsd.&mime_type=video_mp4&qs=15&rc=ODw6OjVpNjc2NGRkZDY0Z0BpM2htbW05cnY6NDMzbzczNUA2XzA2M2E1NjQxNDFhXmNeYSNqczNqMmRrbTNhLS1kMTFzcw%3D%3D&btag=e000b8000&expire=1754625598&l=20250806035941B7B3D5CB1653D912298F&ply_type=2&policy=2&signature=2b6958b1622014716a24d3d05355d59b&tk=tt_chain_token", "protocol": "https", "video_ext": "mp4", "audio_ext": "none", "resolution": "1080x1920", "dynamic_range": "SDR", "aspect_ratio": 0.56, "cookies": "ttwid=1%7ChRi4t0oz-ovVHan5D4N9WD8bWR7Ly3h4oIN--zpKnjM%7C1754452781%7C55b62b40bbf621655ff23ccdd1c622e224871e5c0b32ba6c197c99162a5af0be; Domain=.tiktok.com; Path=/; Expires=1785556781; tt_csrf_token=auPX6IOX-v4ir3CbOFg6Te5XH0ZAu-FjGB7k; Domain=.tiktok.com; Path=/; Secure; tt_chain_token=\"qV5Gmh09CAgPzrFqFuxExA==\"; Domain=.tiktok.com; Path=/; Secure; Expires=1770004781", "http_headers": {"User-Agent": "Mozilla/5.0 (iPhone; CPU iPhone OS 14_6 like Mac OS X) AppleWebKit/605.1.15 (KHTML, like Gecko) Version/14.1.1 Mobile/15E148 Safari/604.1", "Accept": "*/*", "Accept-Language": "en-US,en;q=0.9", "Sec-Fetch-Mode": "navigate", "Accept-Encoding": "gzip, deflate", "Connection": "keep-alive", "Referer": "https://www.tiktok.com/@colorflowlab/video/7515521402238192918"}, "format": "bytevc1_1080p_753210-0 - 1080x1920"}, {"ext": "mp4", "vcodec": "h265", "acodec": "aac", "format_id": "bytevc1_1080p_753210-1", "tbr": 753, "quality": 3, "preference": -1, "filesize": 1541352, "width": 1080, "height": 1920, "url": "https://v19-webapp-prime.us.tiktok.com/video/tos/no1a/tos-no1a-ve-0068-no/ooQenFjIgLA8eRU0AQ4AmwpeIDWn6JmMPiYlcd/?a=1988&bti=ODszNWYuMDE6&ch=0&cr=3&dr=0&lr=all&cd=0%7C0%7C0%7C&cv=1&br=1470&bt=735&cs=2&ds=4&ft=4KJMyMzm8Zmo08eRcI4jV1GjdpWrKsd.&mime_type=video_mp4&qs=15&rc=ODw6OjVpNjc2NGRkZDY0Z0BpM2htbW05cnY6NDMzbzczNUA2XzA2M2E1NjQxNDFhXmNeYSNqczNqMmRrbTNhLS1kMTFzcw%3D%3D&btag=e000b8000&expire=1754625598&l=20250806035941B7B3D5CB1653D912298F&ply_type=2&policy=2&signature=2b6958b1622014716a24d3d05355d59b&tk=tt_chain_token", "protocol": "https", "video_ext": "mp4", "audio_ext": "none", "resolution": "1080x1920", "dynamic_range": "SDR", "aspect_ratio": 0.56, "cookies": "ttwid=1%7ChRi4t0oz-ovVHan5D4N9WD8bWR7Ly3h4oIN--zpKnjM%7C1754452781%7C55b62b40bbf621655ff23ccdd1c622e224871e5c0b32ba6c197c99162a5af0be; Domain=.tiktok.com; Path=/; Expires=1785556781; tt_csrf_token=auPX6IOX-v4ir3CbOFg6Te5XH0ZAu-FjGB7k; Domain=.tiktok.com; Path=/; Secure; tt_chain_token=\"qV5Gmh09CAgPzrFqFuxExA==\"; Domain=.tiktok.com; Path=/; Secure; Expires=1770004781", "http_headers": {"User-Agent": "Mozilla/5.0 (iPhone; CPU iPhone OS 14_6 like Mac OS X) AppleWebKit/605.1.15 (KHTML, like Gecko) Version/14.1.1 Mobile/15E148 Safari/604.1", "Accept": "*/*", "Accept-Language": "en-US,en;q=0.9", "Sec-Fetch-Mode": "navigate", "Accept-Encoding": "gzip, deflate", "Connection": "keep-alive", "Referer": "https://www.tiktok.com/@colorflowlab/video/7515521402238192918"}, "format": "bytevc1_1080p_753210-1 - 1080x1920"}], "subtitles": {}, "http_headers": {"User-Agent": "Mozilla/5.0 (iPhone; CPU iPhone OS 14_6 like Mac OS X) AppleWebKit/605.1.15 (KHTML, like Gecko) Version/14.1.1 Mobile/15E148 Safari/604.1", "Accept": "*/*", "Accept-Language": "en-US,en;q=0.9", "Sec-Fetch-Mode": "navigate", "Accept-Encoding": "gzip, deflate", "Connection": "keep-alive", "Referer": "https://www.tiktok.com/@colorflowlab/video/7515521402238192918"}, "channel": "ColorFlowLab", "channel_id": "MS4wLjABAAAAj28f8A6e_2JAVnXR60xTjriOldLu2SxN4-9CrxJDLVUwDXu7dHkHMfDHFaFg9DcX", "uploader": "colorflowlab", "uploader_id": "7499048455663354913", "channel_url": "https://www.tiktok.com/@MS4wLjABAAAAj28f8A6e_2JAVnXR60xTjriOldLu2SxN4-9CrxJDLVUwDXu7dHkHMfDHFaFg9DcX", "uploader_url": "https://www.tiktok.com/@colorflowlab", "track": "Solitude", "album": "Solitude", "artists": ["juno", "blindheart"], "duration": 16, "title": "Unexpected color recipe✨#colormixing #paintmixing #colortheory #satis...", "description": "Unexpected color recipe✨#colormixing #paintmixing #colortheory #satisfying #colors ", "timestamp": 1749843690, "view_count": 1600000, "like_count": 19800, "repost_count": 160, "comment_count": 155, "thumbnails": [{"id": "dynamicCover", "url": "https://p16-common-sign-no.tiktokcdn-us.com/tos-no1a-p-0037-no/oACRDEgxIMoAnKEsQCYA5kFA0TQcfFfH9tAn7J~tplv-tiktokx-origin.image?dr=9636&x-expires=1754622000&x-signature=8i5dQghhCSkR2PRP5PGyAVykBOQ%3D&t=4d5b0474&ps=13740610&shp=81f88b70&shcp=43f4a2f9&idc=useast5", "preference": -2}, {"id": "cover", "url": "https://p16-common-sign-no.tiktokcdn-us.com/tos-no1a-p-0037-no/oACRDEgxIMoAnKEsQCYA5kFA0TQcfFfH9tAn7J~tplv-tiktokx-origin.image?dr=9636&x-expires=1754622000&x-signature=8i5dQghhCSkR2PRP5PGyAVykBOQ%3D&t=4d5b0474&ps=13740610&shp=81f88b70&shcp=43f4a2f9&idc=useast5", "preference": -1}, {"id": "originCover", "url": "https://p16-common-sign-no.tiktokcdn-us.com/tos-no1a-p-0037-no/oMznQIY0lGAufz7unPLOLjQAqIfAdDdmQTeRYI~tplv-tiktokx-origin.image?dr=9636&x-expires=1754622000&x-signature=7345jkPlTEaFGu%2F%2FeKSN15ipu5o%3D&t=4d5b0474&ps=13740610&shp=81f88b70&shcp=43f4a2f9&idc=useast5", "preference": -1}], "webpage_url": "https://www.tiktok.com/@colorflowlab/video/7515521402238192918?_t=ZS-8ydpcAPrqR5&_r=1", "webpage_url_basename": "7515521402238192918", "webpage_url_domain": "tiktok.com", "extractor": "TikTok", "extractor_key": "TikTok", "thumbnail": "https://p16-common-sign-no.tiktokcdn-us.com/tos-no1a-p-0037-no/oMznQIY0lGAufz7unPLOLjQAqIfAdDdmQTeRYI~tplv-tiktokx-origin.image?dr=9636&x-expires=1754622000&x-signature=7345jkPlTEaFGu%2F%2FeKSN15ipu5o%3D&t=4d5b0474&ps=13740610&shp=81f88b70&shcp=43f4a2f9&idc=useast5", "display_id": "7515521402238192918", "fulltitle": "Unexpected color recipe✨#colormixing #paintmixing #colortheory #satis...", "duration_string": "16", "upload_date": "20250613", "artist": "juno, blindheart", "epoch": 1754452782, "ext": "mp4", "vcodec": "h265", "acodec": "aac", "format_id": "bytevc1_1080p_753210-1", "tbr": 753, "quality": 3, "preference": -1, "filesize": 1541352, "width": 1080, "height": 1920, "url": "https://v19-webapp-prime.us.tiktok.com/video/tos/no1a/tos-no1a-ve-0068-no/ooQenFjIgLA8eRU0AQ4AmwpeIDWn6JmMPiYlcd/?a=1988&bti=ODszNWYuMDE6&ch=0&cr=3&dr=0&lr=all&cd=0%7C0%7C0%7C&cv=1&br=1470&bt=735&cs=2&ds=4&ft=4KJMyMzm8Zmo08eRcI4jV1GjdpWrKsd.&mime_type=video_mp4&qs=15&rc=ODw6OjVpNjc2NGRkZDY0Z0BpM2htbW05cnY6NDMzbzczNUA2XzA2M2E1NjQxNDFhXmNeYSNqczNqMmRrbTNhLS1kMTFzcw%3D%3D&btag=e000b8000&expire=1754625598&l=20250806035941B7B3D5CB1653D912298F&ply_type=2&policy=2&signature=2b6958b1622014716a24d3d05355d59b&tk=tt_chain_token", "protocol": "https", "video_ext": "mp4", "audio_ext": "none", "resolution": "1080x1920", "dynamic_range": "SDR", "aspect_ratio": 0.56, "cookies": "ttwid=1%7ChRi4t0oz-ovVHan5D4N9WD8bWR7Ly3h4oIN--zpKnjM%7C1754452781%7C55b62b40bbf621655ff23ccdd1c622e224871e5c0b32ba6c197c99162a5af0be; Domain=.tiktok.com; Path=/; Expires=1785556781; tt_csrf_token=auPX6IOX-v4ir3CbOFg6Te5XH0ZAu-FjGB7k; Domain=.tiktok.com; Path=/; Secure; tt_chain_token=\"qV5Gmh09CAgPzrFqFuxExA==\"; Domain=.tiktok.com; Path=/; Secure; Expires=1770004781", "format": "bytevc1_1080p_753210-1 - 1080x1920", "_type": "video", "_version": {"version": "2025.07.21", "release_git_head": "9951fdd0d08b655cb1af8cd7f32a3fb7e2b1324e", "repository": "yt-dlp/yt-dlp"}}